salusts/__init__.py
salusts/__main__.py
salusts/nfo.py
salusts/readwrite.py
salusts/tools.py
salusts-2.8.6.dist-info/LICENSE
salusts-2.8.6.dist-info/METADATA
salusts-2.8.6.dist-info/WHEEL
salusts-2.8.6.dist-info/top_level.txt
salusts-2.8.6.dist-info/RECORD
