Metadata-Version: 2.1
Name: salusts
Version: 2.8.6
Summary: A Python package for SaluSTS workflow.
Author-email: HU Xuesong <galaxy001@gmail.com>
License: ISC License
Project-URL: Home-page, https://salus-bio.com/spatial-omics-scope
Keywords: bioinformatics,spRNA-seq,RNA-seq
Classifier: Intended Audience :: Science/Research
Classifier: Natural Language :: English
Classifier: Operating System :: MacOS :: MacOS X
Classifier: Operating System :: POSIX :: Linux
Classifier: Programming Language :: Python :: 3
Classifier: Programming Language :: Python :: 3.9
Classifier: Programming Language :: Python :: 3.10
Classifier: Programming Language :: Python :: 3.11
Classifier: Programming Language :: Python :: 3.12
Classifier: Topic :: Scientific/Engineering :: Bio-Informatics
Requires-Python: >=3.9
License-File: LICENSE
